pyjsonkit/__init__.py
pyjsonkit/ai_processor.py
pyjsonkit/cleaner.py
pyjsonkit/core.py
pyjsonkit/extractor.py
pyjsonkit/parser.py
pyjsonkit/schema_generator.py
pyjsonkit/transformer.py
pyjsonkit/validator.py
pyjsonkit-0.1.0.dist-info/licenses/LICENSE
pyjsonkit-0.1.0.dist-info/METADATA
pyjsonkit-0.1.0.dist-info/WHEEL
pyjsonkit-0.1.0.dist-info/top_level.txt
pyjsonkit-0.1.0.dist-info/RECORD
