Metadata-Version: 2.4
Name: pyjsonkit
Version: 0.1.0
Summary: A comprehensive Python toolkit for JSON processing with advanced AI-focused features for modern data workflows
Author-email: Armaan Shahpuri <armaan30312@gmail.com>
Maintainer-email: Armaan Shahpuri <armaan30312@gmail.com>
License-Expression: MIT
Project-URL: Homepage, https://github.com/Pikachoo1111/jsonkit
Project-URL: Repository, https://github.com/Pikachoo1111/jsonkit.git
Project-URL: Bug Tracker, https://github.com/Pikachoo1111/jsonkit/issues
Keywords: json,ai,ml,data-processing,validation,parsing,extraction,cleaning,transformation,schema-generation
Classifier: Development Status :: 4 - Beta
Classifier: Intended Audience :: Developers
Classifier: Intended Audience :: Science/Research
Classifier: Operating System :: OS Independent
Classifier: Programming Language :: Python :: 3
Classifier: Programming Language :: Python :: 3.8
Classifier: Programming Language :: Python :: 3.9
Classifier: Programming Language :: Python :: 3.10
Classifier: Programming Language :: Python :: 3.11
Classifier: Programming Language :: Python :: 3.12
Classifier: Topic :: Software Development :: Libraries :: Python Modules
Classifier: Topic :: Scientific/Engineering :: Artificial Intelligence
Classifier: Topic :: Text Processing :: Markup
Classifier: Topic :: Utilities
Requires-Python: >=3.8
License-File: LICENSE
Requires-Dist: python-dateutil>=2.8.0
Provides-Extra: dev
Requires-Dist: pytest>=7.0; extra == "dev"
Requires-Dist: pytest-cov>=4.0; extra == "dev"
Requires-Dist: black>=23.0; extra == "dev"
Requires-Dist: isort>=5.0; extra == "dev"
Requires-Dist: flake8>=6.0; extra == "dev"
Requires-Dist: mypy>=1.0; extra == "dev"
Requires-Dist: pre-commit>=3.0; extra == "dev"
Provides-Extra: docs
Requires-Dist: sphinx>=5.0; extra == "docs"
Requires-Dist: sphinx-rtd-theme>=1.0; extra == "docs"
Dynamic: license-file
